labeltext/__init__.py
labeltext/annotate.py
labeltext-0.1.1.dist-info/entry_points.txt
labeltext-0.1.1.dist-info/WHEEL
labeltext-0.1.1.dist-info/METADATA
labeltext-0.1.1.dist-info/RECORD
